arrendatools_ipc/__init__.py
arrendatools_ipc/ine.py
arrendatools_ipc/ipc.py
arrendatools_ipc-1.0.0.dist-info/LICENSE
arrendatools_ipc-1.0.0.dist-info/METADATA
arrendatools_ipc-1.0.0.dist-info/WHEEL
arrendatools_ipc-1.0.0.dist-info/top_level.txt
arrendatools_ipc-1.0.0.dist-info/RECORD
